tcr_boost/__init__.py
tcr_boost-0.1.1.dist-info/LICENSE
tcr_boost-0.1.1.dist-info/METADATA
tcr_boost-0.1.1.dist-info/WHEEL
tcr_boost-0.1.1.dist-info/top_level.txt
tcr_boost-0.1.1.dist-info/RECORD
