Metadata-Version: 2.1
Name: tcr_boost
Version: 0.1.1
Summary: Minimal setup for the tcr_boost package
License: MIT
License-File: LICENSE
